README.rst
setup.py
apiwrapper/__init__.py
bunq_api_sdk.egg-info/PKG-INFO
bunq_api_sdk.egg-info/SOURCES.txt
bunq_api_sdk.egg-info/dependency_links.txt
bunq_api_sdk.egg-info/requires.txt
bunq_api_sdk.egg-info/top_level.txt
tests/__init__.py
tests/runall.py