Metadata-Version: 1.1
Name: bunq-api-sdk
Version: 0.1.3
Summary: A SDK for the Bunq API through which all HTTP requests can be made in a simple manner.
Home-page: https://github.com/PJUllrich/Complete-Bunq-API-Python-Wrapper
Author: Peter Ullrich
Author-email: peter.j.ullrich@gmail.com
License: MIT
Keywords: bunq api wrapper sdk
Platform: UNKNOWN
Classifier: Development Status :: 4 - Beta
Classifier: Topic :: Utilities
Classifier: License :: OSI Approved :: MIT License
